spiki/__init__.py
spiki/__main__.py
spiki/main.py
spiki/plugin.py
spiki/renderer.py
spiki/speechmark.py
spiki/visitor.py
spiki/examples/__init__.py
spiki/examples/atomic/a.toml
spiki/examples/basic/a.toml
spiki/examples/basic/b.toml
spiki/examples/basic/basics.css
spiki/examples/basic/bull-statue-7482855_640.jpg
spiki/examples/basic/c.toml
spiki/examples/basic/index.toml
spiki/examples/basic/layout.css
spiki/examples/basic/lion-671193_640.jpg
spiki/examples/basic/object.css
spiki/examples/basic/spiki.cli
spiki/examples/basic/zen-509371_640.jpg
spiki/examples/cyclic/0834.toml
spiki/examples/cyclic/0836.toml
spiki/examples/cyclic/0838.toml
spiki/examples/cyclic/0840.toml
spiki/examples/cyclic/0842.toml
spiki/examples/cyclic/0844.toml
spiki/examples/cyclic/0846.toml
spiki/examples/cyclic/0848.toml
spiki/examples/cyclic/0850.toml
spiki/examples/cyclic/0852.toml
spiki/examples/cyclic/1136.toml
spiki/examples/cyclic/1176.toml
spiki/examples/cyclic/1218.toml
spiki/examples/cyclic/1266.toml
spiki/examples/cyclic/4510.toml
spiki/examples/cyclic/4578.toml
spiki/examples/cyclic/4646.toml
spiki/examples/cyclic/4720.toml
spiki/examples/cyclic/4806.toml
spiki/examples/cyclic/4892.toml
spiki/examples/cyclic/4984.toml
spiki/examples/cyclic/5082.toml
spiki/examples/cyclic/5194.toml
spiki/examples/cyclic/5304.toml
spiki/examples/cyclic/6003.toml
spiki/examples/cyclic/6127.toml
spiki/examples/cyclic/6265.toml
spiki/examples/cyclic/6401.toml
spiki/examples/cyclic/basics.css
spiki/examples/cyclic/index.toml
spiki/examples/cyclic/layout.css
spiki/examples/cyclic/object.css
spiki/test/__init__.py
spiki/test/test_bootstrapper.py
spiki/test/test_indexer.py
spiki/test/test_loader.py
spiki/test/test_renderer.py
spiki/test/test_speechmark.py
spiki/test/test_visitor.py
spiki-0.17.0.dist-info/licenses/LICENSE
spiki-0.17.0.dist-info/METADATA
spiki-0.17.0.dist-info/WHEEL
spiki-0.17.0.dist-info/entry_points.txt
spiki-0.17.0.dist-info/top_level.txt
spiki-0.17.0.dist-info/RECORD
