Metadata-Version: 2.4
Name: spiki
Version: 0.17.0
Summary: A Wiki for Speech.
Author: D E Haynes
Maintainer-email: Tundish <tundish@gigeconomy.org.uk>
License-Expression: GPL-3.0-or-later
Keywords: wiki,markup,speechmark,template
Classifier: Natural Language :: English
Classifier: Operating System :: OS Independent
Classifier: Environment :: Web Environment
Classifier: Programming Language :: Python :: 3 :: Only
Requires-Python: >=3.12
License-File: LICENSE
Dynamic: license-file
